texthooks/__init__.py
texthooks/_common.py
texthooks/_recorders.py
texthooks/alphabetize_codeowners.py
texthooks/fix_ligatures.py
texthooks/fix_smartquotes.py
texthooks/fix_spaces.py
texthooks/fix_unicode_dashes.py
texthooks/forbid_bidi_controls.py
texthooks/macro_expand.py
texthooks-0.7.1.dist-info/entry_points.txt
texthooks-0.7.1.dist-info/licenses/LICENSE
texthooks-0.7.1.dist-info/WHEEL
texthooks-0.7.1.dist-info/METADATA
texthooks-0.7.1.dist-info/RECORD
