Metadata-Version: 2.4
Name: texthooks
Version: 0.7.1
Summary: pre-commit fixers and linters for handling text files
Keywords: 
Author-email: Stephen Rosen <sirosen0@gmail.com>
Requires-Python: >=3.8
Classifier: Development Status :: 4 - Beta
Classifier: Intended Audience :: Developers
Classifier: License :: OSI Approved :: Apache Software License
Classifier: Programming Language :: Python
Classifier: Programming Language :: Python :: 3.8
Classifier: Programming Language :: Python :: 3.9
Classifier: Programming Language :: Python :: 3.10
Classifier: Programming Language :: Python :: 3.11
Classifier: Programming Language :: Python :: 3.12
License-File: LICENSE
Requires-Dist: identify>=2.0,<3.0
Project-URL: source, https://github.com/sirosen/texthooks
